sermepa/__init__.py
sermepa/sermepa_test.py
sermepa-1.1.3.dist-info/METADATA
sermepa-1.1.3.dist-info/WHEEL
sermepa-1.1.3.dist-info/top_level.txt
sermepa-1.1.3.dist-info/RECORD
