Metadata-Version: 2.1
Name: sermepa
Version: 1.1.3
Summary: A client to submit payment orders to the Sermepa service.
Author-email: Som Energia <itcrowd@somenergia.coop>, Gisce SL <devel@gisce.net>
License: GNU General Public License v3 or later (GPLv3+)
Project-URL: Homepage, https://somenergia.coop
Project-URL: Documentation, https://github.com/som-energia/sermepa
Project-URL: Repository, https://github.com/som-energia/sermepa
Project-URL: Changelog, https://github.com/som-energia/sermepa/blob/master/CHANGELOG.md
Classifier: Programming Language :: Python
Classifier: Programming Language :: Python :: 2
Classifier: Programming Language :: Python :: 3
Classifier: Topic :: Software Development :: Libraries :: Python Modules
Classifier: Intended Audience :: Developers
Classifier: Development Status :: 5 - Production/Stable
Classifier: License :: OSI Approved :: GNU General Public License v2 or later (GPLv2+)
Classifier: Topic :: Office/Business :: Financial
Classifier: Operating System :: OS Independent
Requires-Python: >=2.7
Requires-Dist: pyDes
Requires-Dist: simplejson
Requires-Dist: requests
Requires-Dist: pytest-coverage
